.gitignore
.pylintrc
LICENSE
README.org
default.nix
example.png
nixpkgs.json
setup.py
gitlab_simple.egg-info/PKG-INFO
gitlab_simple.egg-info/SOURCES.txt
gitlab_simple.egg-info/dependency_links.txt
gitlab_simple.egg-info/entry_points.txt
gitlab_simple.egg-info/requires.txt
gitlab_simple.egg-info/top_level.txt
gitlab_simple.egg-info/zip-safe
gitlabsimple/__init__.py
gitlabsimple/__main__.py