Metadata-Version: 1.2
Name: gitlab-simple
Version: 1.2
Summary: Simple GUI for managing GitLab projects
Home-page: https://github.com/plapadoo/gitlab-simple
Author: plapadoo
Author-email: info@plapadoo.de
License: License :: OSI Approved :: GNU General Public License v3 (GPLv3)
Keywords: gitlab
Platform: UNKNOWN
Classifier: Programming Language :: Python :: 3
Requires-Python: >=3.6.1
